foba/__init__.py
foba/dicts/__init__.py
foba/dicts/dict_numbers/__init__.py
foba/dicts/dict_numbers/arm_sales.py
foba/dicts/dict_numbers/brent_prices.py
foba/dicts/dict_numbers/mega_cities.py
foba/dicts/dict_numbers/mortality_rates.py
foba/dicts/dict_numbers/power_cars.py
foba/dicts/dict_numbers/recessions.py
foba/dicts/dict_strings/__init__.py
foba/dicts/dict_strings/car_plants.py
foba/dicts/dict_strings/film_actors.py
foba/dicts/dict_strings/film_actresses.py
foba/dicts/dict_strings/film_directors.py
foba/dicts/dict_strings/military_robots.py
foba/dicts/dict_strings/movie_quotes.py
foba/dicts/dict_strings/pastas.py
foba/dicts/dict_strings/softwoods.py
foba/matrices/__init__.py
foba/matrices/matrix_numbers/__init__.py
foba/matrices/matrix_numbers/functions/__init__.py
foba/matrices/matrix_numbers/functions/identity_matrix.py
foba/matrices/matrix_numbers/functions/pascal_matrix.py
foba/matrices/matrix_numbers/functions/zig_zag_matrix.py
foba/matrices/matrix_strings/CompanyBrandTypes.py
foba/matrices/matrix_strings/Countries.py
foba/matrices/matrix_strings/IntegratedCultureFramework.py
foba/matrices/matrix_strings/MarketingMovement.py
foba/matrices/matrix_strings/__init__.py
foba/objects/__init__.py
foba/objects/point/__init__.py
foba/quotes/__init__.py
foba/tabulars/__init__.py
foba/tabulars/crostabs/AoEIIUnitsAttackByStages.py
foba/tabulars/crostabs/AoEIIUnitsHpByStages.py
foba/tabulars/crostabs/AreaByCountry.py
foba/tabulars/crostabs/BigMacAdjustedIndexes.py
foba/tabulars/crostabs/CountryGDPByYear.py
foba/tabulars/crostabs/FinancialAssetsToGDPByYear.py
foba/tabulars/crostabs/MilitaryByCountry2019.py
foba/tabulars/crostabs/TeachersCountByYear.py
foba/tabulars/crostabs/__init__.py
foba/tabulars/tables/AeroEngineSpecs.py
foba/tabulars/tables/AoEIIUnits.py
foba/tabulars/tables/BigMacAdjustedIndexes.py
foba/tabulars/tables/BistroDutyRoster.py
foba/tabulars/tables/ChinaConceptFirms.py
foba/tabulars/tables/FrontierEconomies.py
foba/tabulars/tables/TopBoxOffice.py
foba-0.0.7.dist-info/WHEEL
foba-0.0.7.dist-info/METADATA
foba-0.0.7.dist-info/RECORD
